girder_large_image_annotation/__init__.py
girder_large_image_annotation/constants.py
girder_large_image_annotation/handlers.py
girder_large_image_annotation/models/__init__.py
girder_large_image_annotation/models/annotation.py
girder_large_image_annotation/models/annotationelement.py
girder_large_image_annotation/rest/__init__.py
girder_large_image_annotation/rest/annotation.py
girder_large_image_annotation/utils/__init__.py
girder_large_image_annotation/web_client/index.js
girder_large_image_annotation/web_client/main.js
girder_large_image_annotation/web_client/package.json
girder_large_image_annotation/web_client/routes.js
girder_large_image_annotation/web_client/annotations/convert.js
girder_large_image_annotation/web_client/annotations/convertFeatures.js
girder_large_image_annotation/web_client/annotations/index.js
girder_large_image_annotation/web_client/annotations/rotate.js
girder_large_image_annotation/web_client/annotations/style.js
girder_large_image_annotation/web_client/annotations/defaults/circle.js
girder_large_image_annotation/web_client/annotations/defaults/ellipse.js
girder_large_image_annotation/web_client/annotations/defaults/index.js
girder_large_image_annotation/web_client/annotations/defaults/point.js
girder_large_image_annotation/web_client/annotations/defaults/polyline.js
girder_large_image_annotation/web_client/annotations/defaults/rectangle.js
girder_large_image_annotation/web_client/annotations/geojs/common.js
girder_large_image_annotation/web_client/annotations/geojs/convert.js
girder_large_image_annotation/web_client/annotations/geojs/index.js
girder_large_image_annotation/web_client/annotations/geojs/coordinates/array.js
girder_large_image_annotation/web_client/annotations/geojs/coordinates/index.js
girder_large_image_annotation/web_client/annotations/geojs/coordinates/point.js
girder_large_image_annotation/web_client/annotations/geojs/types/circle.js
girder_large_image_annotation/web_client/annotations/geojs/types/ellipse.js
girder_large_image_annotation-1.34.0.dist-info/licenses/LICENSE
girder_large_image_annotation-1.34.0.dist-info/METADATA
girder_large_image_annotation-1.34.0.dist-info/WHEEL
girder_large_image_annotation-1.34.0.dist-info/entry_points.txt
girder_large_image_annotation-1.34.0.dist-info/top_level.txt
girder_large_image_annotation-1.34.0.dist-info/RECORD
