Metadata-Version: 2.4
Name: girder-large-image-annotation
Version: 1.34.0
Summary: A Girder plugin to store and display annotations on large, multiresolution images.
Home-page: https://github.com/girder/large_image
Author: Kitware, Inc.
Author-email: kitware@kitware.com
License: Apache-2.0
Keywords: girder-plugin,large_image
Classifier: Development Status :: 5 - Production/Stable
Classifier: Programming Language :: Python :: 3
Classifier: Programming Language :: Python :: 3.10
Classifier: Programming Language :: Python :: 3.11
Classifier: Programming Language :: Python :: 3.12
Classifier: Programming Language :: Python :: 3.13
Classifier: Programming Language :: Python :: 3.14
Requires-Python: >=3.10
License-File: LICENSE
Requires-Dist: jsonschema>=2.5.1
Requires-Dist: girder-large-image>=1.34.0
Requires-Dist: orjson
Provides-Extra: compute
Requires-Dist: openpyxl; extra == "compute"
Requires-Dist: pandas>=2.2; extra == "compute"
Requires-Dist: python-calamine; extra == "compute"
Requires-Dist: umap-learn; extra == "compute"
Provides-Extra: tasks
Requires-Dist: girder-large-image[tasks]>=1.34.0; extra == "tasks"
Dynamic: author
Dynamic: author-email
Dynamic: classifier
Dynamic: description
Dynamic: description-content-type
Dynamic: home-page
Dynamic: keywords
Dynamic: license
Dynamic: license-file
Dynamic: provides-extra
Dynamic: requires-dist
Dynamic: requires-python
Dynamic: summary
